truslyo/__init__.py
truslyo/client.py
truslyo/decorators.py
truslyo/exceptions.py
truslyo/middleware.py
truslyo-1.0.0.dist-info/METADATA
truslyo-1.0.0.dist-info/WHEEL
truslyo-1.0.0.dist-info/top_level.txt
truslyo-1.0.0.dist-info/RECORD
